hotbeak/__init__.py
hotbeak/app.py
hotbeak/test_custom_agent.py
hotbeak/screens/__init__.py
hotbeak/screens/chat_screen.py
hotbeak/screens/parrot_screen.py
hotbeak/services/__init__.py
hotbeak/services/ai_service.py
hotbeak/services/shell_service.py
hotbeak/splash/smoke.txt
hotbeak/splash/weights.txt
hotbeak/styles/styles.tcss
hotbeak/widgets/__init__.py
hotbeak/widgets/approval_input.py
hotbeak/widgets/chat_input.py
hotbeak/widgets/file_search_dropdown.py
hotbeak/widgets/message_list.py
hotbeak/widgets/splash_display.py
hotbeak-0.0.8.dist-info/METADATA
hotbeak-0.0.8.dist-info/WHEEL
hotbeak-0.0.8.dist-info/entry_points.txt
hotbeak-0.0.8.dist-info/top_level.txt
hotbeak-0.0.8.dist-info/RECORD
